{
    "peaks": [
        120.0,
        615.38,
        529.5,
        728.0,
        637.5,
        703.88,
        610.38,
        682.0,
        615.25,
        624.62,
        711.62,
        165.75,
        774.88,
        710.12,
        623.0,
        569.5,
        1559.25,
        972.88,
        714.75,
        529.88,
        476.38,
        736.88,
        521.0,
        1750.88,
        734.75,
        591.5,
        670.75,
        544.25,
        711.38,
        514.5,
        985.75,
        646.25,
        804.5,
        909.5,
        656.0,
        752.12,
        971.25,
        661.25,
        641.25,
        120.12,
        585.0,
        70.88,
        623.12,
        697.62,
        745.12,
        558.5,
        637.62,
        455.88,
        849.75,
        675.12,
        481.0,
        814.0,
        686.75,
        603.38,
        484.75,
        701.88,
        624.25,
        548.75,
        65.5,
        609.83,
        551.83,
        324.83,
        73.83,
        65.0,
        555.67,
        574.33,
        604.83,
        469.0,
        684.0,
        485.5,
        684.83,
        525.17,
        668.17,
        695.33,
        605.17,
        598.33,
        687.67,
        597.83,
        635.0,
        451.33,
        723.83,
        588.0,
        547.0,
        699.5,
        771.17,
        499.17,
        526.17,
        69.33,
        607.33,
        768.0,
        442.83,
        616.0,
        660.67,
        685.5,
        767.0,
        720.17,
        490.83,
        70.0,
        597.5,
        556.33,
        651.0,
        680.33,
        558.33,
        447.67,
        785.83,
        134.5,
        688.83,
        592.67,
        674.67,
        696.17,
        507.5,
        579.0,
        612.0,
        748.0,
        601.67
    ],
    "all harmonic freqs": [
        451.33,
        490.83,
        547.0,
        601.67,
        603.38,
        615.38,
        684.0,
        687.67,
        701.88,
        703.88,
        736.88,
        752.12,
        768.0,
        785.83,
        804.5
    ],
    "group0": [
        [
            603.38,
            703.88,
            768.0,
            804.5
        ],
        "{603.38: [(703.88, Fraction(6, 7)), (768.0, Fraction(11, 14)), (804.5, Fraction(3, 4))], 703.88: [(603.38, Fraction(7, 6)), (768.0, Fraction(11, 12)), (804.5, Fraction(7, 8))], 768.0: [(603.38, Fraction(14, 11)), (703.88, Fraction(12, 11)), (804.5, Fraction(21, 22))], 804.5: [(603.38, Fraction(4, 3)), (703.88, Fraction(8, 7)), (768.0, Fraction(22, 21))]}"
    ],
    "group1": [
        [
            451.33,
            601.67,
            701.88,
            752.12
        ],
        "{451.33: [(601.67, Fraction(3, 4)), (701.88, Fraction(9, 14)), (752.12, Fraction(3, 5))], 601.67: [(451.33, Fraction(4, 3)), (701.88, Fraction(6, 7)), (752.12, Fraction(4, 5))], 701.88: [(451.33, Fraction(14, 9)), (601.67, Fraction(7, 6)), (752.12, Fraction(14, 15))], 752.12: [(451.33, Fraction(5, 3)), (601.67, Fraction(5, 4)), (701.88, Fraction(15, 14))]}"
    ],
    "group2": [
        [
            547.0,
            615.38,
            684.0,
            752.12
        ],
        "{547.0: [(615.38, Fraction(8, 9)), (684.0, Fraction(4, 5)), (752.12, Fraction(8, 11))], 615.38: [(547.0, Fraction(9, 8)), (684.0, Fraction(9, 10)), (752.12, Fraction(9, 11))], 684.0: [(547.0, Fraction(5, 4)), (615.38, Fraction(10, 9)), (752.12, Fraction(10, 11))], 752.12: [(547.0, Fraction(11, 8)), (615.38, Fraction(11, 9)), (684.0, Fraction(11, 10))]}"
    ],
    "group3": [
        [
            490.83,
            687.67,
            736.88,
            785.83
        ],
        "{490.83: [(687.67, Fraction(5, 7)), (736.88, Fraction(2, 3)), (785.83, Fraction(5, 8))], 687.67: [(490.83, Fraction(7, 5)), (736.88, Fraction(14, 15)), (785.83, Fraction(7, 8))], 736.88: [(490.83, Fraction(3, 2)), (687.67, Fraction(15, 14)), (785.83, Fraction(15, 16))], 785.83: [(490.83, Fraction(8, 5)), (687.67, Fraction(8, 7)), (736.88, Fraction(16, 15))]}"
    ]
}